README.rst
setup.py
eldam/__init__.py
eldam/elasticdatamanager.py
eldam.egg-info/PKG-INFO
eldam.egg-info/SOURCES.txt
eldam.egg-info/dependency_links.txt
eldam.egg-info/requires.txt
eldam.egg-info/top_level.txt