Metadata-Version: 1.1
Name: eldam
Version: 1.3.0
Summary: Elastic Search transaction based data manager.
Home-page: https://github.com/bemineni/edm
Author: Srikanth Bemineni
Author-email: srikanth.bemineni@gmail.com
License: MIT
Keywords: ElasticSearch Data manager Development
Platform: UNKNOWN
Classifier: Development Status :: 5 - Production/Stable
Classifier: Intended Audience :: Developers
Classifier: Topic :: Database
Classifier: License :: OSI Approved :: MIT License
Classifier: Programming Language :: Python :: 3.3
Classifier: Programming Language :: Python :: 3.4
Classifier: Programming Language :: Python :: 3.5
